{
  "title": {
    "id": "tt0831387",
    "type": "movie",
    "is_adult": false,
    "primary_title": "Godzilla",
    "original_title": null,
    "start_year": 2014,
    "end_year": null,
    "runtime_minutes": 123,
    "plot": "The world is beset by the appearance of monstrous creatures, but one of them may be the only one who can save humanity.",
    "rating": {
      "aggregate_rating": 6.4,
      "votes_count": 435597
    },
    "genres": [
      "Action",
      "Adventure",
      "Sci-Fi",
      "Thriller"
    ],
    "posters": [
      {
        "url": "https://m.media-amazon.com/images/M/MV5BZDFmYTM4NzAtNWM0ZC00MGJlLWEyYzQtYzA3ZTFiNzc1YjllXkEyXkFqcGdeQXVyMTA4NjE0NjEy._V1_.jpg",
        "width": 1000,
        "height": 1500
      }
    ],
    "certificates": [
      {
        "country": {
          "code": "US",
          "name": "United States"
        },
        "rating": "PG-13"
      }
    ],
    "spoken_languages": [
      {
        "code": "eng",
        "name": "English"
      },
      {
        "code": "jpn",
        "name": "Japanese"
      }
    ],
    "origin_countries": [
      {
        "code": "JP",
        "name": "Japan"
      },
      {
        "code": "US",
        "name": "United States"
      }
    ],
    "critic_review": {
      "score": 62,
      "review_count": 48
    },
    "directors": [
      {
        "name": {
          "id": "nm2284484",
          "display_name": "Gareth Edwards",
          "avatars": [
            {
              "url": "https://m.media-amazon.com/images/M/MV5BMjAyMjU1MjIzOF5BMl5BanBnXkFtZTcwNDY5ODYxNA@@._V1_.jpg",
              "width": 258,
              "height": 400
            }
          ]
        }
      }
    ],
    "writers": [
      {
        "name": {
          "id": "nm0393094",
          "display_name": "Ishirô Honda",
          "avatars": [
            {
              "url": "https://m.media-amazon.com/images/M/MV5BYzFmYmJhODgtODdiNS00Nzc5LWI0ZWEtZDJiOGRjMjFiOWE5XkEyXkFqcGdeQXVyNzY1ODU1OTk@._V1_.jpg",
              "width": 774,
              "height": 1062
            }
          ]
        }
      },
      {
        "name": {
          "id": "nm0613609",
          "display_name": "Takeo Murata",
          "avatars": null
        }
      },
      {
        "name": {
          "id": "nm0443227",
          "display_name": "Shigeru Kayama",
          "avatars": null
        }
      },
      {
        "name": {
          "id": "nm1709264",
          "display_name": "Dave Callaham",
          "avatars": [
            {
              "url": "https://m.media-amazon.com/images/M/MV5BOTgwODBmZTItMGZmYi00MWY2LTllZjMtZDc4YjM0NzRmMjNhXkEyXkFqcGdeQXVyNDEzMDkzOQ@@._V1_.jpg",
              "width": 986,
              "height": 1276
            }
          ]
        }
      },
      {
        "name": {
          "id": "nm1440919",
          "display_name": "Max Borenstein",
          "avatars": [
            {
              "url": "https://m.media-amazon.com/images/M/MV5BMzRkY2M1YTEtNGMzYi00ZWIxLWIwN2YtOGFlMzU2MmE0Y2ViXkEyXkFqcGdeQXVyMjk3NTUyOTc@._V1_.jpg",
              "width": 349,
              "height": 524
            }
          ]
        }
      }
    ],
    "casts": [
      {
        "name": {
          "id": "nm1093951",
          "display_name": "Aaron Taylor-Johnson",
          "avatars": [
            {
              "url": "https://m.media-amazon.com/images/M/MV5BMzE5MzI0MzY2OF5BMl5BanBnXkFtZTgwODE3MTk4MTE@._V1_.jpg",
              "width": 1375,
              "height": 1805
            }
          ]
        },
        "characters": [
          "Ford Brody"
        ]
      },
      {
        "name": {
          "id": "nm2640264",
          "display_name": "CJ Adams",
          "avatars": [
            {
              "url": "https://m.media-amazon.com/images/M/MV5BZDg3OWNkN2UtMjRhNi00NWJjLWJmNzEtMzEyMDAyODk0ZmZkXkEyXkFqcGdeQXVyMjQxNTg5ODk@._V1_.jpg",
              "width": 4000,
              "height": 6000
            }
          ]
        },
        "characters": [
          "Young Ford"
        ]
      },
      {
        "name": {
          "id": "nm0913822",
          "display_name": "Ken Watanabe",
          "avatars": [
            {
              "url": "https://m.media-amazon.com/images/M/MV5BMTQzMTUzNjc4Nl5BMl5BanBnXkFtZTcwMTUyODU2Mw@@._V1_.jpg",
              "width": 277,
              "height": 400
            }
          ]
        },
        "characters": [
          "Dr. Ishiro Serizawa"
        ]
      },
      {
        "name": {
          "id": "nm0186505",
          "display_name": "Bryan Cranston",
          "avatars": [
            {
              "url": "https://m.media-amazon.com/images/M/MV5BMTA2NjEyMTY4MTVeQTJeQWpwZ15BbWU3MDQ5NDAzNDc@._V1_.jpg",
              "width": 1369,
              "height": 2048
            }
          ]
        },
        "characters": [
          "Joe Brody"
        ]
      },
      {
        "name": {
          "id": "nm0647634",
          "display_name": "Elizabeth Olsen",
          "avatars": [
            {
              "url": "https://m.media-amazon.com/images/M/MV5BMjEzMjA0ODk1OF5BMl5BanBnXkFtZTcwMTA4ODM3OQ@@._V1_.jpg",
              "width": 640,
              "height": 899
            }
          ]
        },
        "characters": [
          "Elle Brody"
        ]
      },
      {
        "name": {
          "id": "nm3395766",
          "display_name": "Carson Bolde",
          "avatars": [
            {
              "url": "https://m.media-amazon.com/images/M/MV5BYTY3ZGQ3N2MtMmIyZS00ZWJhLWIwYjUtM2IwN2EzMWNiMzRlXkEyXkFqcGdeQXVyMjA0MTAxMjY@._V1_.jpg",
              "width": 2400,
              "height": 3600
            }
          ]
        },
        "characters": [
          "Sam Brody"
        ]
      },
      {
        "name": {
          "id": "nm1020089",
          "display_name": "Sally Hawkins",
          "avatars": [
            {
              "url": "https://m.media-amazon.com/images/M/MV5BODE4MDE0MDEzMl5BMl5BanBnXkFtZTgwNjI1NTU5MDE@._V1_.jpg",
              "width": 1567,
              "height": 2048
            }
          ]
        },
        "characters": [
          "Vivienne Graham"
        ]
      },
      {
        "name": {
          "id": "nm0000300",
          "display_name": "Juliette Binoche",
          "avatars": [
            {
              "url": "https://m.media-amazon.com/images/M/MV5BMTUzMzI4MDQ5Nl5BMl5BanBnXkFtZTYwOTQ5NTc0._V1_.jpg",
              "width": 266,
              "height": 400
            }
          ]
        },
        "characters": [
          "Sandra Brody"
        ]
      },
      {
        "name": {
          "id": "nm0000657",
          "display_name": "David Strathairn",
          "avatars": [
            {
              "url": "https://m.media-amazon.com/images/M/MV5BNmQ2ZDY1ZGUtODM2OC00ZTMzLWIyMTQtMzk1NzAwZGQ3MWIzXkEyXkFqcGdeQXVyMjQwMDg0Ng@@._V1_.jpg",
              "width": 398,
              "height": 600
            }
          ]
        },
        "characters": [
          "Admiral William Stenz"
        ]
      },
      {
        "name": {
          "id": "nm0429114",
          "display_name": "Richard T. Jones",
          "avatars": [
            {
              "url": "https://m.media-amazon.com/images/M/MV5BMTc5NjcwNDk0Nl5BMl5BanBnXkFtZTcwODgxMjMwMg@@._V1_.jpg",
              "width": 653,
              "height": 452
            }
          ]
        },
        "characters": [
          "Captain Russell Hampton"
        ]
      },
      {
        "name": {
          "id": "nm0711559",
          "display_name": "Victor Rasuk",
          "avatars": [
            {
              "url": "https://m.media-amazon.com/images/M/MV5BMjEyNDg3ODE0MV5BMl5BanBnXkFtZTgwMTU2NTgxMDE@._V1_.jpg",
              "width": 274,
              "height": 400
            }
          ]
        },
        "characters": [
          "Sergeant Tre Morales"
        ]
      },
      {
        "name": {
          "id": "nm1150775",
          "display_name": "Patrick Sabongui",
          "avatars": [
            {
              "url": "https://m.media-amazon.com/images/M/MV5BZTgyYmQ2MTYtZjEzZC00MzM3LWFhYTgtMGY0Mjk5MWYyMjFmXkEyXkFqcGdeQXVyNTMzOTU5Mg@@._V1_.jpg",
              "width": 8272,
              "height": 6200
            }
          ]
        },
        "characters": [
          "Lieutenant Commander Marcus Waltz"
        ]
      },
      {
        "name": {
          "id": "nm1742119",
          "display_name": "Jared Keeso",
          "avatars": [
            {
              "url": "https://m.media-amazon.com/images/M/MV5BM2UzNmM0YjEtNzcwNi00MDlkLTlmNGMtODQ5YWQ1OTlhYjRlXkEyXkFqcGdeQXVyODkwNTAxOTU@._V1_.jpg",
              "width": 874,
              "height": 1164
            }
          ]
        },
        "characters": [
          "Jump Master"
        ]
      },
      {
        "name": {
          "id": "nm3526638",
          "display_name": "Luc Roderique",
          "avatars": [
            {
              "url": "https://m.media-amazon.com/images/M/MV5BYjA2M2U2ZDUtZTRjYy00ZjA4LWE4YjAtZDIyYTA0Y2Q4NTQ1XkEyXkFqcGdeQXVyMjQwMDg0Ng@@._V1_.jpg",
              "width": 3405,
              "height": 4800
            }
          ]
        },
        "characters": [
          "Bomb Tracker"
        ]
      },
      {
        "name": {
          "id": "nm2101229",
          "display_name": "James Pizzinato",
          "avatars": [
            {
              "url": "https://m.media-amazon.com/images/M/MV5BYjFhMjAxZTItMzlmMy00Y2E1LWFmMGUtNjRjN2ZiZTIxMGQ1XkEyXkFqcGdeQXVyNjAzNjE4OQ@@._V1_.jpg",
              "width": 2549,
              "height": 3823
            }
          ]
        },
        "characters": [
          "HALO Jumper"
        ]
      }
    ]
  }
}