{
  "title": {
    "id": "tt1124037",
    "type": "movie",
    "is_adult": false,
    "primary_title": "Free State of Jones",
    "original_title": null,
    "start_year": 2016,
    "end_year": null,
    "runtime_minutes": 139,
    "plot": "A disillusioned Confederate army deserter returns to Mississippi and leads a militia of fellow deserters and women in an uprising against the corrupt local Confederate government.",
    "rating": {
      "aggregate_rating": 6.9,
      "votes_count": 62515
    },
    "genres": [
      "Action",
      "Biography",
      "Drama",
      "History",
      "War",
      "Western"
    ],
    "posters": [
      {
        "url": "https://m.media-amazon.com/images/M/MV5BMTA4NTYyMTcwNTFeQTJeQWpwZ15BbWU4MDI0NTg0MDkx._V1_.jpg",
        "width": 1038,
        "height": 1500
      }
    ],
    "certificates": [
      {
        "country": {
          "code": "US",
          "name": "United States"
        },
        "rating": "R"
      }
    ],
    "spoken_languages": [
      {
        "code": "eng",
        "name": "English"
      }
    ],
    "origin_countries": [
      {
        "code": "US",
        "name": "United States"
      }
    ],
    "critic_review": {
      "score": 53,
      "review_count": 38
    },
    "directors": [
      {
        "name": {
          "id": "nm0002657",
          "display_name": "Gary Ross",
          "avatars": [
            {
              "url": "https://m.media-amazon.com/images/M/MV5BMTI3NjcxMTA2Nl5BMl5BanBnXkFtZTcwMjkwNDYyMQ@@._V1_.jpg",
              "width": 300,
              "height": 420
            }
          ]
        }
      }
    ],
    "writers": [
      {
        "name": {
          "id": "nm0002657",
          "display_name": "Gary Ross",
          "avatars": [
            {
              "url": "https://m.media-amazon.com/images/M/MV5BMTI3NjcxMTA2Nl5BMl5BanBnXkFtZTcwMjkwNDYyMQ@@._V1_.jpg",
              "width": 300,
              "height": 420
            }
          ]
        }
      },
      {
        "name": {
          "id": "nm0366989",
          "display_name": "Leonard Hartman",
          "avatars": [
            {
              "url": "https://m.media-amazon.com/images/M/MV5BZmU5NWUxY2MtMGNiZi00N2I2LWI1ZmQtOTNjNjMzOWI0OWM3XkEyXkFqcGc@._V1_.jpg",
              "width": 169,
              "height": 250
            }
          ]
        }
      }
    ],
    "casts": [
      {
        "name": {
          "id": "nm0000190",
          "display_name": "Matthew McConaughey",
          "avatars": [
            {
              "url": "https://m.media-amazon.com/images/M/MV5BMTg0MDc3ODUwOV5BMl5BanBnXkFtZTcwMTk2NjY4Nw@@._V1_.jpg",
              "width": 1256,
              "height": 2048
            }
          ]
        },
        "characters": [
          "Newton Knight"
        ]
      },
      {
        "name": {
          "id": "nm1813221",
          "display_name": "Gugu Mbatha-Raw",
          "avatars": [
            {
              "url": "https://m.media-amazon.com/images/M/MV5BM2FlZWVlYWMtMDM5OC00M2IxLWI5ZmYtNzdiNGQ1OTA0MjgzXkEyXkFqcGdeQXVyOTIzNjQ2NjY@._V1_.jpg",
              "width": 1371,
              "height": 1500
            }
          ]
        },
        "characters": [
          "Rachel"
        ]
      },
      {
        "name": {
          "id": "nm0991810",
          "display_name": "Mahershala Ali",
          "avatars": [
            {
              "url": "https://m.media-amazon.com/images/M/MV5BZThiZjJjNWYtNGRlYS00NDdkLTk0MTMtYjEwYzM1MDExNTYwXkEyXkFqcGdeQXVyNjY1MTg4Mzc@._V1_.jpg",
              "width": 3260,
              "height": 3569
            }
          ]
        },
        "characters": [
          "Moses"
        ]
      },
      {
        "name": {
          "id": "nm0005392",
          "display_name": "Keri Russell",
          "avatars": [
            {
              "url": "https://m.media-amazon.com/images/M/MV5BYjcxNjIxOWYtMWY0MS00ZmU4LWE1NGQtYzQ0ZGQ4MmUzZWJiXkEyXkFqcGdeQXVyNTIwMzYwNg@@._V1_.jpg",
              "width": 532,
              "height": 805
            }
          ]
        },
        "characters": [
          "Serena"
        ]
      },
      {
        "name": {
          "id": "nm0077512",
          "display_name": "Christopher Berry",
          "avatars": [
            {
              "url": "https://m.media-amazon.com/images/M/MV5BYmZkNGRjYmItMzUwZi00ODA4LWFkNjctOGIxM2NmYjEzOTdmXkEyXkFqcGdeQXVyMjQwMDg0Ng@@._V1_.jpg",
              "width": 695,
              "height": 927
            }
          ]
        },
        "characters": [
          "Jasper Collins"
        ]
      },
      {
        "name": {
          "id": "nm0108703",
          "display_name": "Sean Bridgers",
          "avatars": [
            {
              "url": "https://m.media-amazon.com/images/M/MV5BNTE5NjY5ZTktZWU4ZC00NTNhLWI1ZTktMzEwOTgzN2UyN2E5XkEyXkFqcGdeQXVyNjUxMjc1OTM@._V1_.jpg",
              "width": 2297,
              "height": 3000
            }
          ]
        },
        "characters": [
          "Will Sumrall"
        ]
      },
      {
        "name": {
          "id": "nm5015107",
          "display_name": "Jacob Lofland",
          "avatars": [
            {
              "url": "https://m.media-amazon.com/images/M/MV5BMTgyMDYwODcxOV5BMl5BanBnXkFtZTgwMzIxNjY4MDI@._V1_.jpg",
              "width": 1000,
              "height": 1500
            }
          ]
        },
        "characters": [
          "Daniel"
        ]
      },
      {
        "name": {
          "id": "nm2958419",
          "display_name": "Thomas Francis Murphy",
          "avatars": [
            {
              "url": "https://m.media-amazon.com/images/M/MV5BOGI5ZDNmNjItNTA2MS00YTlhLTg4ODMtNTk4YzZkYzYyN2Y3XkEyXkFqcGdeQXVyMjQwMDg0Ng@@._V1_.jpg",
              "width": 903,
              "height": 1268
            }
          ]
        },
        "characters": [
          "Elias Hood"
        ]
      },
      {
        "name": {
          "id": "nm1813729",
          "display_name": "Bill Tangradi",
          "avatars": [
            {
              "url": "https://m.media-amazon.com/images/M/MV5BNjg4NjU0OTMxNV5BMl5BanBnXkFtZTcwMjg4ODkyOQ@@._V1_.jpg",
              "width": 653,
              "height": 435
            }
          ]
        },
        "characters": [
          "Lt. Barbour"
        ]
      },
      {
        "name": {
          "id": "nm0291368",
          "display_name": "Brian Lee Franklin",
          "avatars": [
            {
              "url": "https://m.media-amazon.com/images/M/MV5BZjM2NjUxNjgtNzY0Yy00YjdmLWJjNjYtYjA3MTVlMzJiMzFlXkEyXkFqcGc@._V1_.jpg",
              "width": 3264,
              "height": 4896
            }
          ]
        },
        "characters": [
          "Davis Knight"
        ]
      },
      {
        "name": {
          "id": "nm2684369",
          "display_name": "Kerry Cahill",
          "avatars": [
            {
              "url": "https://m.media-amazon.com/images/M/MV5BYWFlMDdiMDQtYWU2Zi00YjIxLWE0YjAtNjRjNTY3OGQ3OTFmXkEyXkFqcGdeQXVyNjc5Mjg0NjU@._V1_.jpg",
              "width": 4500,
              "height": 3000
            }
          ]
        },
        "characters": [
          "Mary",
          "Yeoman Farmer"
        ]
      },
      {
        "name": {
          "id": "nm0159609",
          "display_name": "Joe Chrest",
          "avatars": [
            {
              "url": "https://m.media-amazon.com/images/M/MV5BZjY4NTJlNjktMWQzNy00NDVhLWJkOGUtNWZmNWUxMzEzYTdmXkEyXkFqcGdeQXVyMjIxNzUxMjY@._V1_.jpg",
              "width": 1165,
              "height": 1645
            }
          ]
        },
        "characters": [
          "James Eakins"
        ]
      },
      {
        "name": {
          "id": "nm2193754",
          "display_name": "Jessica Ann Collins",
          "avatars": [
            {
              "url": "https://m.media-amazon.com/images/M/MV5BMjE3ZmI5Y2YtMjNlMC00NWJjLThhYzItZTZlNjVmZGJhZjgzXkEyXkFqcGdeQXVyMTEzNjc3MDQ5._V1_.jpg",
              "width": 449,
              "height": 650
            }
          ]
        },
        "characters": [
          "Annie"
        ]
      },
      {
        "name": {
          "id": "nm5060159",
          "display_name": "Donald Elise Watkins",
          "avatars": [
            {
              "url": "https://m.media-amazon.com/images/M/MV5BOTI4YjYwOTEtMWNhOS00M2VkLTlkYmItMzc5OWFlMzI2MWIwXkEyXkFqcGdeQXVyMzA2ODA0OTk@._V1_.jpg",
              "width": 4480,
              "height": 6720
            }
          ]
        },
        "characters": [
          "Wilson"
        ]
      },
      {
        "name": {
          "id": "nm0166232",
          "display_name": "Jill Jane Clements",
          "avatars": [
            {
              "url": "https://m.media-amazon.com/images/M/MV5BNjIyOGJkYWYtNzZmNy00ZjFkLWI3YmYtZTczNGIwOTlkOGQwXkEyXkFqcGdeQXVyMTA1MTkxMzMx._V1_.jpg",
              "width": 1824,
              "height": 2736
            }
          ]
        },
        "characters": [
          "Aunt Sally"
        ]
      }
    ]
  }
}