{
  "title": {
    "id": "tt1489889",
    "type": "movie",
    "is_adult": false,
    "primary_title": "Central Intelligence",
    "original_title": null,
    "start_year": 2016,
    "end_year": null,
    "runtime_minutes": 107,
    "plot": "After he reconnects with an awkward pal from high school through Facebook, a mild-mannered accountant is lured into the world of international espionage.",
    "rating": {
      "aggregate_rating": 6.3,
      "votes_count": 213679
    },
    "genres": [
      "Action",
      "Comedy",
      "Crime"
    ],
    "posters": [
      {
        "url": "https://m.media-amazon.com/images/M/MV5BMjA2NzEzNjIwNl5BMl5BanBnXkFtZTgwNzgwMTEzNzE@._V1_.jpg",
        "width": 1382,
        "height": 2048
      }
    ],
    "certificates": [
      {
        "country": {
          "code": "US",
          "name": "United States"
        },
        "rating": "PG-13"
      }
    ],
    "spoken_languages": [
      {
        "code": "eng",
        "name": "English"
      }
    ],
    "origin_countries": [
      {
        "code": "CN",
        "name": "China"
      },
      {
        "code": "US",
        "name": "United States"
      }
    ],
    "critic_review": {
      "score": 52,
      "review_count": 35
    },
    "directors": [
      {
        "name": {
          "id": "nm1098493",
          "display_name": "Rawson Marshall Thurber",
          "avatars": [
            {
              "url": "https://m.media-amazon.com/images/M/MV5BOTQ1ZTI3ODItODU3OS00YWZiLTkxY2QtYjMxODQ5MWViMmYzXkEyXkFqcGdeQXVyMDI3ODUxMQ@@._V1_.jpg",
              "width": 3749,
              "height": 4686
            }
          ]
        }
      }
    ],
    "writers": [
      {
        "name": {
          "id": "nm0054697",
          "display_name": "Ike Barinholtz",
          "avatars": [
            {
              "url": "https://m.media-amazon.com/images/M/MV5BMjE1NDY0NjMwOV5BMl5BanBnXkFtZTgwMDE4MTYxMDI@._V1_.jpg",
              "width": 691,
              "height": 1024
            }
          ]
        }
      },
      {
        "name": {
          "id": "nm2811682",
          "display_name": "David Stassen",
          "avatars": [
            {
              "url": "https://m.media-amazon.com/images/M/MV5BMTUzMjU4MjY0N15BMl5BanBnXkFtZTgwOTYwMzcxOTE@._V1_.jpg",
              "width": 1994,
              "height": 3000
            }
          ]
        }
      },
      {
        "name": {
          "id": "nm1098493",
          "display_name": "Rawson Marshall Thurber",
          "avatars": [
            {
              "url": "https://m.media-amazon.com/images/M/MV5BOTQ1ZTI3ODItODU3OS00YWZiLTkxY2QtYjMxODQ5MWViMmYzXkEyXkFqcGdeQXVyMDI3ODUxMQ@@._V1_.jpg",
              "width": 3749,
              "height": 4686
            }
          ]
        }
      }
    ],
    "casts": [
      {
        "name": {
          "id": "nm0425005",
          "display_name": "Dwayne Johnson",
          "avatars": [
            {
              "url": "https://m.media-amazon.com/images/M/MV5BOWU1ODBiNGUtMzVjNi00MzdhLTk0OTktOWRiOTIxMWNhOGI2XkEyXkFqcGdeQXVyMTU2OTM5NDQw._V1_.jpg",
              "width": 5464,
              "height": 8192
            }
          ]
        },
        "characters": [
          "Bob Stone"
        ]
      },
      {
        "name": {
          "id": "nm0366389",
          "display_name": "Kevin Hart",
          "avatars": [
            {
              "url": "https://m.media-amazon.com/images/M/MV5BMTY4OTAxMjkxN15BMl5BanBnXkFtZTgwODg5MzYyMTE@._V1_.jpg",
              "width": 1362,
              "height": 2048
            }
          ]
        },
        "characters": [
          "Calvin Joyner"
        ]
      },
      {
        "name": {
          "id": "nm0752407",
          "display_name": "Amy Ryan",
          "avatars": [
            {
              "url": "https://m.media-amazon.com/images/M/MV5BMTY0MTcwMzM0Nl5BMl5BanBnXkFtZTcwODIyMjM3NA@@._V1_.jpg",
              "width": 1376,
              "height": 1976
            }
          ]
        },
        "characters": [
          "Agent Pamela Harris"
        ]
      },
      {
        "name": {
          "id": "nm0630379",
          "display_name": "Danielle Nicolet",
          "avatars": [
            {
              "url": "https://m.media-amazon.com/images/M/MV5BYmRhMGI2MTAtNGQ3MC00MTk5LWExMGEtYjYyODRkNjE4ZWQ1XkEyXkFqcGdeQXVyMDE4NTY1Mw@@._V1_.jpg",
              "width": 1280,
              "height": 1757
            }
          ]
        },
        "characters": [
          "Maggie"
        ]
      },
      {
        "name": {
          "id": "nm0000867",
          "display_name": "Jason Bateman",
          "avatars": [
            {
              "url": "https://m.media-amazon.com/images/M/MV5BMTMwOTQ0MDUyNF5BMl5BanBnXkFtZTcwNTQ1MzY1Mw@@._V1_.jpg",
              "width": 315,
              "height": 400
            }
          ]
        },
        "characters": [
          "Trevor"
        ]
      },
      {
        "name": {
          "id": "nm0666739",
          "display_name": "Aaron Paul",
          "avatars": [
            {
              "url": "https://m.media-amazon.com/images/M/MV5BMTY1OTY5NjI5NV5BMl5BanBnXkFtZTcwODA4MjM0OA@@._V1_.jpg",
              "width": 681,
              "height": 1024
            }
          ]
        },
        "characters": [
          "Phil"
        ]
      },
      {
        "name": {
          "id": "nm1218621",
          "display_name": "Ryan Hansen",
          "avatars": [
            {
              "url": "https://m.media-amazon.com/images/M/MV5BNjU4NDE2NjgxOF5BMl5BanBnXkFtZTgwMjQ1MTA1MDE@._V1_.jpg",
              "width": 399,
              "height": 599
            }
          ]
        },
        "characters": [
          "Steve"
        ]
      },
      {
        "name": {
          "id": "nm0341377",
          "display_name": "Tim Griffin",
          "avatars": [
            {
              "url": "https://m.media-amazon.com/images/M/MV5BOTliMTc1YTItYmVkMi00YTkxLTg5MWEtZWQwNzdiZWVhZmFlXkEyXkFqcGdeQXVyMjQwMDg0Ng@@._V1_.jpg",
              "width": 1734,
              "height": 2600
            }
          ]
        },
        "characters": [
          "Agent Stan Mitchell"
        ]
      },
      {
        "name": {
          "id": "nm6326385",
          "display_name": "Timothy John Smith",
          "avatars": [
            {
              "url": "https://m.media-amazon.com/images/M/MV5BN2NiN2ZjN2EtNjI5MS00ODBjLWFhNGUtZDc4YWQ2ZDFjNGY2XkEyXkFqcGdeQXVyMjQwMDg0Ng@@._V1_.jpg",
              "width": 788,
              "height": 640
            }
          ]
        },
        "characters": [
          "Agent Nick Cooper"
        ]
      },
      {
        "name": {
          "id": "nm7063789",
          "display_name": "Sione Kelepi",
          "avatars": null
        },
        "characters": [
          "Young Robbie"
        ]
      },
      {
        "name": {
          "id": "nm3876372",
          "display_name": "Dylan Boyack",
          "avatars": null
        },
        "characters": [
          "Trevor - 17 Years Old"
        ]
      },
      {
        "name": {
          "id": "nm0470981",
          "display_name": "Thomas Kretschmann",
          "avatars": [
            {
              "url": "https://m.media-amazon.com/images/M/MV5BMTY1Njc5MzE1OF5BMl5BanBnXkFtZTcwMTc1NDM4Nw@@._V1_.jpg",
              "width": 1431,
              "height": 2048
            }
          ]
        },
        "characters": [
          "The Buyer"
        ]
      },
      {
        "name": {
          "id": "nm1177914",
          "display_name": "Megan Park",
          "avatars": [
            {
              "url": "https://m.media-amazon.com/images/M/MV5BMjgwNDE5NzU4M15BMl5BanBnXkFtZTgwNTcyNTQ0MDI@._V1_.jpg",
              "width": 1536,
              "height": 1024
            }
          ]
        },
        "characters": [
          "Waitress"
        ]
      },
      {
        "name": {
          "id": "nm2282835",
          "display_name": "George Carroll",
          "avatars": [
            {
              "url": "https://m.media-amazon.com/images/M/MV5BZmUwZmNlOWQtMzI1ZC00ZjgxLTk5YjctZGQzYTJjOTZiYzQ2XkEyXkFqcGdeQXVyMjEzMjMzNDc@._V1_.jpg",
              "width": 1698,
              "height": 2400
            }
          ]
        },
        "characters": [
          "Thugged Out"
        ]
      },
      {
        "name": {
          "id": "nm4826061",
          "display_name": "Annie Kerins",
          "avatars": [
            {
              "url": "https://m.media-amazon.com/images/M/MV5BZWY1MDAxYTktMGZiYS00YTQyLTk3MTQtYzZhMzViNDE3NDg0XkEyXkFqcGdeQXVyMzI5NjMwNzM@._V1_.jpg",
              "width": 4357,
              "height": 6535
            }
          ]
        },
        "characters": [
          "Lady MC"
        ]
      }
    ]
  }
}