{
  "title": {
    "id": "tt2385104",
    "type": "movie",
    "is_adult": false,
    "primary_title": "D-Day",
    "original_title": null,
    "start_year": 2013,
    "end_year": null,
    "runtime_minutes": 153,
    "plot": "A team of experts dispatched to bring in The Most Wanted Man in India almost achieve the unthinkable ... until something goes horribly wrong.",
    "rating": {
      "aggregate_rating": 7.2,
      "votes_count": 10394
    },
    "genres": [
      "Action",
      "Thriller"
    ],
    "posters": [
      {
        "url": "https://m.media-amazon.com/images/M/MV5BMTk4MDQzMjU3M15BMl5BanBnXkFtZTcwMDY1NzA4OQ@@._V1_.jpg",
        "width": 750,
        "height": 1083
      }
    ],
    "certificates": [
      {
        "country": {
          "code": "US",
          "name": "United States"
        },
        "rating": "Not Rated"
      }
    ],
    "spoken_languages": [
      {
        "code": "hin",
        "name": "Hindi"
      }
    ],
    "origin_countries": [
      {
        "code": "IN",
        "name": "India"
      }
    ],
    "critic_review": null,
    "directors": [
      {
        "name": {
          "id": "nm0012541",
          "display_name": "Nikkhil Advani",
          "avatars": [
            {
              "url": "https://m.media-amazon.com/images/M/MV5BYmE1ZDU3M2MtOTE4MC00NjU1LTg1NzctMzc3MDBiNmE1MmNlXkEyXkFqcGdeQXVyNTg3MzU3ODQ@._V1_.jpg",
              "width": 5034,
              "height": 4444
            }
          ]
        }
      }
    ],
    "writers": [
      {
        "name": {
          "id": "nm0012541",
          "display_name": "Nikkhil Advani",
          "avatars": [
            {
              "url": "https://m.media-amazon.com/images/M/MV5BYmE1ZDU3M2MtOTE4MC00NjU1LTg1NzctMzc3MDBiNmE1MmNlXkEyXkFqcGdeQXVyNTg3MzU3ODQ@._V1_.jpg",
              "width": 5034,
              "height": 4444
            }
          ]
        }
      },
      {
        "name": {
          "id": "nm1937760",
          "display_name": "Ritesh Shah",
          "avatars": null
        }
      },
      {
        "name": {
          "id": "nm1330994",
          "display_name": "Suresh Nair",
          "avatars": null
        }
      },
      {
        "name": {
          "id": "nm1145539",
          "display_name": "Niranjan Iyengar",
          "avatars": null
        }
      }
    ],
    "casts": [
      {
        "name": {
          "id": "nm0438501",
          "display_name": "Rishi Kapoor",
          "avatars": [
            {
              "url": "https://m.media-amazon.com/images/M/MV5BMjJmNjM1YmUtNTA2Zi00Y2U0LTgyZTItMjQ5MTE4NWJhMDgyXkEyXkFqcGdeQXVyMTExNDQ2MTI@._V1_.jpg",
              "width": 534,
              "height": 694
            }
          ]
        },
        "characters": [
          "Goldman"
        ]
      },
      {
        "name": {
          "id": "nm0451234",
          "display_name": "Irrfan Khan",
          "avatars": [
            {
              "url": "https://m.media-amazon.com/images/M/MV5BNDg3NDgxNzY4NF5BMl5BanBnXkFtZTcwODMxODQzMg@@._V1_.jpg",
              "width": 299,
              "height": 400
            }
          ]
        },
        "characters": [
          "Wali Khan"
        ]
      },
      {
        "name": {
          "id": "nm0992000",
          "display_name": "Arjun Rampal",
          "avatars": [
            {
              "url": "https://m.media-amazon.com/images/M/MV5BZmRmZDhjMjUtYmE0MC00ZTQ2LTllZjEtZjA1OTU2ZTg3YWVhXkEyXkFqcGdeQXVyMTU0ODI1NTA2._V1_.jpg",
              "width": 615,
              "height": 1024
            }
          ]
        },
        "characters": [
          "Rudra Pratap"
        ]
      },
      {
        "name": {
          "id": "nm11138211",
          "display_name": "Asif Silavat",
          "avatars": [
            {
              "url": "https://m.media-amazon.com/images/M/MV5BNjZkMjQyY2UtYmViNC00YmZjLTg1ZDItMGM0NWYwMWE3YzZlXkEyXkFqcGc@._V1_CR413,631,697,1046_.jpg",
              "width": 697,
              "height": 1046
            }
          ]
        },
        "characters": [
          "Cop at Airport"
        ]
      },
      {
        "name": {
          "id": "nm1599046",
          "display_name": "Shruti Haasan",
          "avatars": [
            {
              "url": "https://m.media-amazon.com/images/M/MV5BNTg5MjM0YWUtZGU3Yy00MDM2LThjYmEtYzAzMmM1MzhhNDdkXkEyXkFqcGdeQXVyMzQ0NTk5NzU@._V1_.jpg",
              "width": 1716,
              "height": 2573
            }
          ]
        },
        "characters": [
          "Suraiya"
        ]
      },
      {
        "name": {
          "id": "nm4806622",
          "display_name": "Huma Qureshi",
          "avatars": [
            {
              "url": "https://m.media-amazon.com/images/M/MV5BMTEwMTkyMDY3OTheQTJeQWpwZ15BbWU4MDE1MjEyMzkx._V1_.jpg",
              "width": 1365,
              "height": 2048
            }
          ]
        },
        "characters": [
          "Zoya"
        ]
      },
      {
        "name": {
          "id": "nm0621937",
          "display_name": "Nassar",
          "avatars": [
            {
              "url": "https://m.media-amazon.com/images/M/MV5BMjA3Njc5NjcwOF5BMl5BanBnXkFtZTcwMTgyOTY0OA@@._V1_.jpg",
              "width": 2048,
              "height": 1365
            }
          ]
        },
        "characters": [
          "Ashwini Rao"
        ]
      },
      {
        "name": {
          "id": "nm0706953",
          "display_name": "K.K. Raina",
          "avatars": [
            {
              "url": "https://m.media-amazon.com/images/M/MV5BMzY0YmM3YWItN2I1MC00MjcwLWFhMzYtOTA3ZTAzNzdkZTA3XkEyXkFqcGc@._V1_.jpg",
              "width": 475,
              "height": 598
            }
          ]
        },
        "characters": [
          "General Raza"
        ]
      },
      {
        "name": {
          "id": "nm3204740",
          "display_name": "Chandan Roy Sanyal",
          "avatars": [
            {
              "url": "https://m.media-amazon.com/images/M/MV5BMjlmZDE1YTAtZDhjZi00YjE5LWE0NWYtODExYTc5NmE0ZmI5L2ltYWdlL2ltYWdlXkEyXkFqcGdeQXVyMTExNDQ2MTI@._V1_.jpg",
              "width": 1456,
              "height": 1992
            }
          ]
        },
        "characters": [
          "Bhanja"
        ]
      },
      {
        "name": {
          "id": "nm2246740",
          "display_name": "Imran Hasnee",
          "avatars": [
            {
              "url": "https://m.media-amazon.com/images/M/MV5BZGQ5ZWI3MDYtYjM0YS00NTRiLTgzMDktMTdjZmQxODQ4YmE2XkEyXkFqcGc@._V1_.jpg",
              "width": 1200,
              "height": 1800
            }
          ]
        },
        "characters": [
          "Saleem Pathan"
        ]
      },
      {
        "name": {
          "id": "nm0451281",
          "display_name": "Nissar Khan",
          "avatars": [
            {
              "url": "https://m.media-amazon.com/images/M/MV5BZDJiMGMwYzgtZDk4My00MTQ5LTgxMTgtYmVlODFjODg1YTFhXkEyXkFqcGc@._V1_.jpg",
              "width": 459,
              "height": 508
            }
          ]
        },
        "characters": [
          "Niyaaz Ahmed"
        ]
      },
      {
        "name": {
          "id": "nm1276263",
          "display_name": "Sandeep Kulkarni",
          "avatars": [
            {
              "url": "https://m.media-amazon.com/images/M/MV5BMDAwMzliNTgtMTQ4ZS00N2E1LWJiMzUtZjk2ZjJjOTFjMWMyXkEyXkFqcGc@._V1_.jpg",
              "width": 3456,
              "height": 5184
            }
          ]
        },
        "characters": [
          "Anup Mishra"
        ]
      },
      {
        "name": {
          "id": "nm3721371",
          "display_name": "Aakash Dahiya",
          "avatars": [
            {
              "url": "https://m.media-amazon.com/images/M/MV5BYmU3ZTI5YTctYjZmMi00YmIxLTgwOTgtNDVlNmMwNTY1MDhiXkEyXkFqcGc@._V1_.jpg",
              "width": 2786,
              "height": 3072
            }
          ]
        },
        "characters": [
          "Aslam"
        ]
      },
      {
        "name": {
          "id": "nm4496860",
          "display_name": "Divji Handa",
          "avatars": null
        },
        "characters": [
          "Kabeer"
        ]
      },
      {
        "name": {
          "id": "nm5546451",
          "display_name": "Shriswara",
          "avatars": [
            {
              "url": "https://m.media-amazon.com/images/M/MV5BYjU0YTFkZGUtNmNkZi00YzVmLTk5NWYtZmUwNzgyNjYwZWU1XkEyXkFqcGc@._V1_.jpg",
              "width": 3647,
              "height": 5472
            }
          ]
        },
        "characters": [
          "Nafisa"
        ]
      }
    ]
  }
}