{
  "title": {
    "id": "tt5580036",
    "type": "movie",
    "is_adult": false,
    "primary_title": "I, Tonya",
    "original_title": null,
    "start_year": 2017,
    "end_year": null,
    "runtime_minutes": 119,
    "plot": "Competitive ice skater Tonya Harding rises amongst the ranks at the U.S. Figure Skating Championships, but her future in the activity is thrown into doubt when her ex-husband intervenes.",
    "rating": {
      "aggregate_rating": 7.5,
      "votes_count": 243068
    },
    "genres": [
      "Biography",
      "Comedy",
      "Drama",
      "Sport"
    ],
    "posters": [
      {
        "url": "https://m.media-amazon.com/images/M/MV5BMjI5MDY1NjYzMl5BMl5BanBnXkFtZTgwNjIzNDAxNDM@._V1_.jpg",
        "width": 1012,
        "height": 1500
      }
    ],
    "certificates": [
      {
        "country": {
          "code": "US",
          "name": "United States"
        },
        "rating": "R"
      }
    ],
    "spoken_languages": [
      {
        "code": "eng",
        "name": "English"
      }
    ],
    "origin_countries": [
      {
        "code": "GB",
        "name": "United Kingdom"
      },
      {
        "code": "US",
        "name": "United States"
      }
    ],
    "critic_review": {
      "score": 77,
      "review_count": 47
    },
    "directors": [
      {
        "name": {
          "id": "nm0318916",
          "display_name": "Craig Gillespie",
          "avatars": [
            {
              "url": "https://m.media-amazon.com/images/M/MV5BMTI3MTEwNDAxNF5BMl5BanBnXkFtZTcwNzk1OTc1MQ@@._V1_.jpg",
              "width": 339,
              "height": 400
            }
          ]
        }
      }
    ],
    "writers": [
      {
        "name": {
          "id": "nm0737216",
          "display_name": "Steven Rogers",
          "avatars": [
            {
              "url": "https://m.media-amazon.com/images/M/MV5BODQ0OTAxNTQ1NV5BMl5BanBnXkFtZTgwMTI0ODUwNjE@._V1_.jpg",
              "width": 427,
              "height": 640
            }
          ]
        }
      }
    ],
    "casts": [
      {
        "name": {
          "id": "nm3053338",
          "display_name": "Margot Robbie",
          "avatars": [
            {
              "url": "https://m.media-amazon.com/images/M/MV5BMTgxNDcwMzU2Nl5BMl5BanBnXkFtZTcwNDc4NzkzOQ@@._V1_.jpg",
              "width": 1000,
              "height": 1332
            }
          ]
        },
        "characters": [
          "Tonya"
        ]
      },
      {
        "name": {
          "id": "nm1659221",
          "display_name": "Sebastian Stan",
          "avatars": [
            {
              "url": "https://m.media-amazon.com/images/M/MV5BNTk2OGU4NzktODhhOC00Nzc2LWIyNzYtOWViMjljZGFiNTMxXkEyXkFqcGdeQXVyMTE1NTQwOTk@._V1_.jpg",
              "width": 3300,
              "height": 4293
            }
          ]
        },
        "characters": [
          "Jeff"
        ]
      },
      {
        "name": {
          "id": "nm0005049",
          "display_name": "Allison Janney",
          "avatars": [
            {
              "url": "https://m.media-amazon.com/images/M/MV5BMjAyNjc2NzgxM15BMl5BanBnXkFtZTgwODQyMjM1MjE@._V1_.jpg",
              "width": 1496,
              "height": 2048
            }
          ]
        },
        "characters": [
          "LaVona"
        ]
      },
      {
        "name": {
          "id": "nm0629855",
          "display_name": "Julianne Nicholson",
          "avatars": [
            {
              "url": "https://m.media-amazon.com/images/M/MV5BMjM1NDk3MTQ1N15BMl5BanBnXkFtZTgwMDMwODEyMDE@._V1_.jpg",
              "width": 2048,
              "height": 1360
            }
          ]
        },
        "characters": [
          "Diane Rawlinson"
        ]
      },
      {
        "name": {
          "id": "nm3236159",
          "display_name": "Paul Walter Hauser",
          "avatars": [
            {
              "url": "https://m.media-amazon.com/images/M/MV5BZWU4OWExZjktMzJmZC00YjY4LWI1ZTYtOWU1OGU1YTVjODU0XkEyXkFqcGdeQXVyMjk0NjI0MQ@@._V1_.jpg",
              "width": 5976,
              "height": 3984
            }
          ]
        },
        "characters": [
          "Shawn"
        ]
      },
      {
        "name": {
          "id": "nm0134072",
          "display_name": "Bobby Cannavale",
          "avatars": [
            {
              "url": "https://m.media-amazon.com/images/M/MV5BMTU0NzM3MzQ4Ml5BMl5BanBnXkFtZTgwOTg2MjY4ODE@._V1_.jpg",
              "width": 693,
              "height": 390
            }
          ]
        },
        "characters": [
          "Martin Maddox"
        ]
      },
      {
        "name": {
          "id": "nm0636942",
          "display_name": "Bojana Novakovic",
          "avatars": [
            {
              "url": "https://m.media-amazon.com/images/M/MV5BNmZmNmM4MjItMjg3Yi00YmQwLTg1YjUtYWFjMTcyYTJiYTQwXkEyXkFqcGdeQXVyOTUwNjgxMDY@._V1_.jpg",
              "width": 2871,
              "height": 3600
            }
          ]
        },
        "characters": [
          "Dody Teachman"
        ]
      },
      {
        "name": {
          "id": "nm4850403",
          "display_name": "Caitlin Carver",
          "avatars": [
            {
              "url": "https://m.media-amazon.com/images/M/MV5BY2ZlODFlM2ItNWEwZS00YzE1LWFlMGYtZDlkOGY2ZDlmNzM4XkEyXkFqcGdeQXVyMzA0NTcxMjI@._V1_.jpg",
              "width": 558,
              "height": 800
            }
          ]
        },
        "characters": [
          "Nancy Kerrigan"
        ]
      },
      {
        "name": {
          "id": "nm7431107",
          "display_name": "Maizie Smith",
          "avatars": null
        },
        "characters": [
          "Tonya (3 1",
          "2 Yrs)"
        ]
      },
      {
        "name": {
          "id": "nm5085683",
          "display_name": "Mckenna Grace",
          "avatars": [
            {
              "url": "https://m.media-amazon.com/images/M/MV5BMzI4Y2EzNTEtZWZiZS00NzZmLTlmZWYtNGUwYmE3YjliOWQ5XkEyXkFqcGdeQXVyMzQxNjUxMDE@._V1_.jpg",
              "width": 1600,
              "height": 2400
            }
          ]
        },
        "characters": [
          "Tonya (8-12 Yrs)"
        ]
      },
      {
        "name": {
          "id": "nm2612326",
          "display_name": "Suehyla El-Attar Young",
          "avatars": [
            {
              "url": "https://m.media-amazon.com/images/M/MV5BZGFiZDk1MTAtNmQwMi00NmI0LWFkOGMtOWNjZTQxNzc5ZGRkXkEyXkFqcGdeQXVyMzgxMDQ0MzY@._V1_.jpg",
              "width": 1638,
              "height": 2048
            }
          ]
        },
        "characters": [
          "Skater Mom"
        ]
      },
      {
        "name": {
          "id": "nm1151921",
          "display_name": "Jason Davis",
          "avatars": [
            {
              "url": "https://m.media-amazon.com/images/M/MV5BMWU3N2YwNjQtNmQxOC00NjQ5LTlmMWMtOTY5NmQ0NTY1MWQ0XkEyXkFqcGdeQXVyNjUxMjc1OTM@._V1_.jpg",
              "width": 1280,
              "height": 536
            }
          ]
        },
        "characters": [
          "Al"
        ]
      },
      {
        "name": {
          "id": "nm7556188",
          "display_name": "Mea Allen",
          "avatars": [
            {
              "url": "https://m.media-amazon.com/images/M/MV5BMGU1MTU2NzEtOThjMS00MDQ3LWJlOTgtN2YzNDE3MTUwODE1XkEyXkFqcGc@._V1_.jpg",
              "width": 1638,
              "height": 2048
            }
          ]
        },
        "characters": [
          "Snooty Girl"
        ]
      },
      {
        "name": {
          "id": "nm5302034",
          "display_name": "Cory Chapman",
          "avatars": [
            {
              "url": "https://m.media-amazon.com/images/M/MV5BMDg0ZTBiYWMtMDVhMi00MDYwLTg3ZTItMzFiNmY4ZjE2NmRhL2ltYWdlL2ltYWdlXkEyXkFqcGdeQXVyMzM4MjM0Nzg@._V1_.jpg",
              "width": 399,
              "height": 600
            }
          ]
        },
        "characters": [
          "Chris"
        ]
      },
      {
        "name": {
          "id": "nm4707742",
          "display_name": "Amy Fox",
          "avatars": [
            {
              "url": "https://m.media-amazon.com/images/M/MV5BZDg4MmQyZWUtYjE5Zi00YWIwLThmMmMtM2MzZThjM2EzZmFjXkEyXkFqcGc@._V1_.jpg",
              "width": 2400,
              "height": 3598
            }
          ]
        },
        "characters": [
          "Skating Judge"
        ]
      }
    ]
  }
}