{
  "title": {
    "id": "tt8265928",
    "type": "movie",
    "is_adult": false,
    "primary_title": "Love at Second Sight",
    "original_title": "Mon inconnue",
    "start_year": 2019,
    "end_year": null,
    "runtime_minutes": 117,
    "plot": "A man tries to make his wife fall in love with him again, after waking up in an alternate reality where she never knew him.",
    "rating": {
      "aggregate_rating": 6.9,
      "votes_count": 6213
    },
    "genres": [
      "Comedy",
      "Drama",
      "Fantasy",
      "Romance"
    ],
    "posters": [
      {
        "url": "https://m.media-amazon.com/images/M/MV5BNmQ3NjdkMDQtNmM1Zi00MjI0LTk4ZTMtYTdjYjI1Y2Q4NGVlXkEyXkFqcGdeQXVyNTc5OTMwOTQ@._V1_.jpg",
        "width": 795,
        "height": 1080
      }
    ],
    "certificates": null,
    "spoken_languages": [
      {
        "code": "eng",
        "name": "English"
      },
      {
        "code": "fra",
        "name": "French"
      }
    ],
    "origin_countries": [
      {
        "code": "BE",
        "name": "Belgium"
      },
      {
        "code": "FR",
        "name": "France"
      },
      {
        "code": "KR",
        "name": "Republic of Korea"
      }
    ],
    "critic_review": null,
    "directors": [
      {
        "name": {
          "id": "nm0312315",
          "display_name": "Hugo Gélin",
          "avatars": [
            {
              "url": "https://m.media-amazon.com/images/M/MV5BYTdmODNlOWUtYzQwZi00MjRlLWEwMDEtMmZmZWExYjE1MDgxXkEyXkFqcGdeQXVyMTAyMzg0OA@@._V1_.jpg",
              "width": 1280,
              "height": 960
            }
          ]
        }
      }
    ],
    "writers": [
      {
        "name": {
          "id": "nm0312315",
          "display_name": "Hugo Gélin",
          "avatars": [
            {
              "url": "https://m.media-amazon.com/images/M/MV5BYTdmODNlOWUtYzQwZi00MjRlLWEwMDEtMmZmZWExYjE1MDgxXkEyXkFqcGdeQXVyMTAyMzg0OA@@._V1_.jpg",
              "width": 1280,
              "height": 960
            }
          ]
        }
      },
      {
        "name": {
          "id": "nm0331868",
          "display_name": "Igor Gotesman",
          "avatars": null
        }
      },
      {
        "name": {
          "id": "nm4874812",
          "display_name": "Benjamin Parent",
          "avatars": null
        }
      },
      {
        "name": {
          "id": "nm0172989",
          "display_name": "Laetitia Colombani",
          "avatars": null
        }
      },
      {
        "name": {
          "id": "nm2271931",
          "display_name": "David Foenkinos",
          "avatars": null
        }
      }
    ],
    "casts": [
      {
        "name": {
          "id": "nm2476624",
          "display_name": "François Civil",
          "avatars": [
            {
              "url": "https://m.media-amazon.com/images/M/MV5BODI4ODIzNzQ5OV5BMl5BanBnXkFtZTgwODM3MDAwMTE@._V1_.jpg",
              "width": 1360,
              "height": 2048
            }
          ]
        },
        "characters": [
          "Raphaël Ramisse",
          "Zoltan"
        ]
      },
      {
        "name": {
          "id": "nm1754147",
          "display_name": "Joséphine Japy",
          "avatars": [
            {
              "url": "https://m.media-amazon.com/images/M/MV5BZGU5NTcxYTktNmZmZi00NTA3LTgzZDAtZWRjOTcyYjVkNjVmXkEyXkFqcGdeQXVyMTExMTc3NzU5._V1_.jpg",
              "width": 810,
              "height": 1312
            }
          ]
        },
        "characters": [
          "Olivia Marigny",
          "Shadow"
        ]
      },
      {
        "name": {
          "id": "nm3118835",
          "display_name": "Benjamin Lavernhe",
          "avatars": [
            {
              "url": "https://m.media-amazon.com/images/M/MV5BZWQ2NDFhYTMtMTQ5MS00ZjQzLTk5YzYtYjU0MDAzOWJkZThjXkEyXkFqcGdeQXVyNjUwNzk3NDc@._V1_.jpg",
              "width": 676,
              "height": 976
            }
          ]
        },
        "characters": [
          "Félix",
          "Gumpar"
        ]
      },
      {
        "name": {
          "id": "nm5674012",
          "display_name": "Camille Lellouche",
          "avatars": null
        },
        "characters": [
          "Mélanie"
        ]
      },
      {
        "name": {
          "id": "nm2611421",
          "display_name": "Amaury de Crayencour",
          "avatars": null
        },
        "characters": [
          "Marc Deschanel"
        ]
      },
      {
        "name": {
          "id": "nm0778568",
          "display_name": "Edith Scob",
          "avatars": [
            {
              "url": "https://m.media-amazon.com/images/M/MV5BODE5NTY4NDcyNl5BMl5BanBnXkFtZTcwMTc3MzQ4Nw@@._V1_.jpg",
              "width": 1362,
              "height": 2048
            }
          ]
        },
        "characters": [
          "Gabrielle, la grand-mère"
        ]
      },
      {
        "name": {
          "id": "nm3325973",
          "display_name": "Juliette Dol",
          "avatars": null
        },
        "characters": [
          "Morgane"
        ]
      },
      {
        "name": {
          "id": "nm1822041",
          "display_name": "Samir Boitard",
          "avatars": [
            {
              "url": "https://m.media-amazon.com/images/M/MV5BY2QxNzUyY2MtMDNjYS00ZmVmLTg1MTctZGNiMDcyNDVkNTRlXkEyXkFqcGdeQXVyMTY3NTY5OTcx._V1_.jpg",
              "width": 485,
              "height": 692
            }
          ]
        },
        "characters": [
          "Le prof de lettres",
          "Le chef des mercenaires"
        ]
      },
      {
        "name": {
          "id": "nm0070694",
          "display_name": "Christian Benedetti",
          "avatars": null
        },
        "characters": [
          "Etienne Robert, l'éditeur"
        ]
      },
      {
        "name": {
          "id": "nm1397399",
          "display_name": "Guillaume Bouchède",
          "avatars": null
        },
        "characters": [
          "Le fan inconditionnel d'Olivia"
        ]
      },
      {
        "name": {
          "id": "nm5367226",
          "display_name": "Anne-Valérie Payet",
          "avatars": null
        },
        "characters": [
          "Assistante Olivia"
        ]
      },
      {
        "name": {
          "id": "nm2218926",
          "display_name": "Raphael von Blumenthal",
          "avatars": null
        },
        "characters": [
          "Producteur américain réunion éditeur"
        ]
      },
      {
        "name": {
          "id": "nm2794927",
          "display_name": "Bertrand Combe",
          "avatars": null
        },
        "characters": [
          "Proviseur lycée"
        ]
      },
      {
        "name": {
          "id": "nm3801695",
          "display_name": "Guillaume Mélanie",
          "avatars": [
            {
              "url": "https://m.media-amazon.com/images/M/MV5BMTM3OTI2OGUtN2MyYi00YmZhLWEzZjEtM2EyY2Y0NGJiZTFjXkEyXkFqcGc@._V1_.jpg",
              "width": 431,
              "height": 610
            }
          ]
        },
        "characters": [
          "Régisseur Odéon"
        ]
      },
      {
        "name": {
          "id": "nm10435032",
          "display_name": "Sonia Nini",
          "avatars": null
        },
        "characters": [
          "Sandra la livreuse"
        ]
      }
    ]
  }
}