{
  "title": {
    "id": "tt9271672",
    "type": "movie",
    "is_adult": false,
    "primary_title": "Prey for the Devil",
    "original_title": null,
    "start_year": 2022,
    "end_year": null,
    "runtime_minutes": 93,
    "plot": "A nun prepares to perform an exorcism and comes face to face with a demonic force with mysterious ties to her past.",
    "rating": {
      "aggregate_rating": 5.3,
      "votes_count": 17644
    },
    "genres": [
      "Horror",
      "Mystery",
      "Thriller"
    ],
    "posters": [
      {
        "url": "https://m.media-amazon.com/images/M/MV5BNzNjNmE4YTktMTZiNS00YTQ0LWExY2YtZTU2MGNiNzBiMzI5XkEyXkFqcGdeQXVyMTA0OTI1NDM2._V1_.jpg",
        "width": 1480,
        "height": 2192
      }
    ],
    "certificates": [
      {
        "country": {
          "code": "US",
          "name": "United States"
        },
        "rating": "PG-13"
      }
    ],
    "spoken_languages": [
      {
        "code": "bul",
        "name": "Bulgarian"
      },
      {
        "code": "eng",
        "name": "English"
      },
      {
        "code": "lat",
        "name": "Latin"
      },
      {
        "code": "spa",
        "name": "Spanish"
      }
    ],
    "origin_countries": [
      {
        "code": "US",
        "name": "United States"
      }
    ],
    "critic_review": {
      "score": 38,
      "review_count": 5
    },
    "directors": [
      {
        "name": {
          "id": "nm0821844",
          "display_name": "Daniel Stamm",
          "avatars": [
            {
              "url": "https://m.media-amazon.com/images/M/MV5BMTc5Mjg2MjI3N15BMl5BanBnXkFtZTgwMTY1NDUzMTE@._V1_.jpg",
              "width": 2048,
              "height": 1413
            }
          ]
        }
      }
    ],
    "writers": [
      {
        "name": {
          "id": "nm0002526",
          "display_name": "Robert Zappia",
          "avatars": [
            {
              "url": "https://m.media-amazon.com/images/M/MV5BM2Q3MDEwMTgtZTU0NC00NjgxLWJiOWYtMmE2M2M5ZjZmYzI0XkEyXkFqcGdeQXVyMzU0ODg4Mw@@._V1_.jpg",
              "width": 709,
              "height": 709
            }
          ]
        }
      },
      {
        "name": {
          "id": "nm0427993",
          "display_name": "Earl Richey Jones",
          "avatars": null
        }
      },
      {
        "name": {
          "id": "nm5333675",
          "display_name": "Todd R. Jones",
          "avatars": null
        }
      }
    ],
    "casts": [
      {
        "name": {
          "id": "nm1859932",
          "display_name": "Jacqueline Byers",
          "avatars": [
            {
              "url": "https://m.media-amazon.com/images/M/MV5BMDhjNzliNWQtMDhmYy00YzI3LWIwM2YtNDdhMmU2M2RjZTJiXkEyXkFqcGdeQXVyNDUxNzA4NTY@._V1_.jpg",
              "width": 750,
              "height": 1136
            }
          ]
        },
        "characters": [
          "Ann"
        ]
      },
      {
        "name": {
          "id": "nm10682687",
          "display_name": "Debora Zhecheva",
          "avatars": [
            {
              "url": "https://m.media-amazon.com/images/M/MV5BMDc3NWY0MDktMTI1Ni00ZTlmLTk3YTktNmM5ZDRhYzU0NmUyXkEyXkFqcGdeQXVyMjQwMDg0Ng@@._V1_.jpg",
              "width": 1366,
              "height": 1911
            }
          ]
        },
        "characters": [
          "Young Ann"
        ]
      },
      {
        "name": {
          "id": "nm2111303",
          "display_name": "Christian Navarro",
          "avatars": [
            {
              "url": "https://m.media-amazon.com/images/M/MV5BOTZiOTc4OWQtYjQ5MC00MmVjLTk5OTYtMDE4MWQ5OWJkYTI3XkEyXkFqcGdeQXVyNTI5NjIyMw@@._V1_.jpg",
              "width": 641,
              "height": 960
            }
          ]
        },
        "characters": [
          "Father Dante"
        ]
      },
      {
        "name": {
          "id": "nm12071421",
          "display_name": "Posy Taylor",
          "avatars": [
            {
              "url": "https://m.media-amazon.com/images/M/MV5BNTExMzg4MWQtMmY2OC00MzMwLWExMWItMTU1NTY2ZDM4YmQyXkEyXkFqcGc@._V1_.jpg",
              "width": 2000,
              "height": 3000
            }
          ]
        },
        "characters": [
          "Natalie"
        ]
      },
      {
        "name": {
          "id": "nm0758760",
          "display_name": "Colin Salmon",
          "avatars": [
            {
              "url": "https://m.media-amazon.com/images/M/MV5BMzYzMjNiMjgtN2M1My00ZDNmLTg2M2UtZmI0YmMyMDZkOWQ1XkEyXkFqcGdeQXVyMTExNDQ2MTI@._V1_.jpg",
              "width": 968,
              "height": 1346
            }
          ]
        },
        "characters": [
          "Father Quinn"
        ]
      },
      {
        "name": {
          "id": "nm11013770",
          "display_name": "Nicholas Ralph",
          "avatars": [
            {
              "url": "https://m.media-amazon.com/images/M/MV5BMTA2YmQwMjgtMmRlMC00YjM0LTkwMTctZTc2YmM5ODdlMTc5XkEyXkFqcGdeQXVyODQ1MjE1MDk@._V1_.jpg",
              "width": 1155,
              "height": 1232
            }
          ]
        },
        "characters": [
          "Father Raymond"
        ]
      },
      {
        "name": {
          "id": "nm0002027",
          "display_name": "Ben Cross",
          "avatars": [
            {
              "url": "https://m.media-amazon.com/images/M/MV5BMTkxMTkxMDcxNV5BMl5BanBnXkFtZTcwOTg0NjM1Mg@@._V1_.jpg",
              "width": 286,
              "height": 400
            }
          ]
        },
        "characters": [
          "Cardinal Matthews"
        ]
      },
      {
        "name": {
          "id": "nm0000515",
          "display_name": "Virginia Madsen",
          "avatars": [
            {
              "url": "https://m.media-amazon.com/images/M/MV5BNjUyMDcxNTU3N15BMl5BanBnXkFtZTcwMDAwNjQzMg@@._V1_.jpg",
              "width": 266,
              "height": 400
            }
          ]
        },
        "characters": [
          "Dr. Peters"
        ]
      },
      {
        "name": {
          "id": "nm0657648",
          "display_name": "Lisa Palfrey",
          "avatars": [
            {
              "url": "https://m.media-amazon.com/images/M/MV5BYjk0NTk3NmUtOWU0MC00Y2Y1LTg3NDQtMTZiNzU0YzhiODhkXkEyXkFqcGdeQXVyMzczMzAzMTE@._V1_.jpg",
              "width": 1189,
              "height": 1712
            }
          ]
        },
        "characters": [
          "Sister Euphemia"
        ]
      },
      {
        "name": {
          "id": "nm0825029",
          "display_name": "Koyna Ruseva",
          "avatars": [
            {
              "url": "https://m.media-amazon.com/images/M/MV5BZjc3NTliYTYtY2Y2My00NzIwLWExMWItYWVlMGRiNjY5OTFjXkEyXkFqcGdeQXVyMTI2NTY5MzEz._V1_.jpg",
              "width": 1145,
              "height": 1600
            }
          ]
        },
        "characters": [
          "Ann's Mother"
        ]
      },
      {
        "name": {
          "id": "nm8230647",
          "display_name": "Cora Kirk",
          "avatars": [
            {
              "url": "https://m.media-amazon.com/images/M/MV5BNWJmOGJjNjgtM2U5MS00ZWQ4LWFhZGUtMzUyMWUzYjE5NWI0XkEyXkFqcGdeQXVyNjc2NzQ5MTk@._V1_.jpg",
              "width": 6336,
              "height": 9504
            }
          ]
        },
        "characters": [
          "Emilia"
        ]
      },
      {
        "name": {
          "id": "nm11987894",
          "display_name": "Elizabeth Gibson",
          "avatars": [
            {
              "url": "https://m.media-amazon.com/images/M/MV5BNWMwYTBkYzctNjdlNy00MDVhLThhZWItMjEwODEwYjJmNTdjXkEyXkFqcGc@._V1_.jpg",
              "width": 1093,
              "height": 1638
            }
          ]
        },
        "characters": [
          "Sister Kylie"
        ]
      },
      {
        "name": {
          "id": "nm0082870",
          "display_name": "Velizar Binev",
          "avatars": [
            {
              "url": "https://m.media-amazon.com/images/M/MV5BMTIzMjUwOTk3OF5BMl5BanBnXkFtZTcwNzYyMTIzMQ@@._V1_.jpg",
              "width": 450,
              "height": 630
            }
          ]
        },
        "characters": [
          "Father Bernhard"
        ]
      },
      {
        "name": {
          "id": "nm2810106",
          "display_name": "Yana Marinova",
          "avatars": [
            {
              "url": "https://m.media-amazon.com/images/M/MV5BYTRhMjY1MTgtNDQzZi00YzdkLWJmMzEtNjVhNTMzNWViZmJmXkEyXkFqcGdeQXVyMjA4MjcyNzg@._V1_.jpg",
              "width": 853,
              "height": 853
            }
          ]
        },
        "characters": [
          "Natalie's Mother"
        ]
      },
      {
        "name": {
          "id": "nm0058844",
          "display_name": "Keith Bartlett",
          "avatars": [
            {
              "url": "https://m.media-amazon.com/images/M/MV5BNGVmNmIyNzYtNTU0MC00MDc3LWIzOTAtMjhmMmNkMWQ1NWEwXkEyXkFqcGc@._V1_.jpg",
              "width": 375,
              "height": 569
            }
          ]
        },
        "characters": [
          "Clark"
        ]
      }
    ]
  }
}